abx_plugin_readability/__init__.py
abx_plugin_readability/binaries.py
abx_plugin_readability/config.py
abx_plugin_readability/extractors.py
abx_plugin_readability/readability.py
abx_plugin_readability-2024.10.28.dist-info/METADATA
abx_plugin_readability-2024.10.28.dist-info/WHEEL
abx_plugin_readability-2024.10.28.dist-info/entry_points.txt
abx_plugin_readability-2024.10.28.dist-info/RECORD
